marcel_socialsentiment/__init__.py
marcel_socialsentiment/marcel_socialsentiment.py
marcel_socialsentiment-2.9.dist-info/METADATA
marcel_socialsentiment-2.9.dist-info/WHEEL
marcel_socialsentiment-2.9.dist-info/top_level.txt
marcel_socialsentiment-2.9.dist-info/RECORD
