Metadata-Version: 2.1
Name: marcel-socialsentiment
Version: 2.9
Summary: Library to perform Social Sentiment on Unstructured data
Author: Marcel Tino
Author-email: <marceltino92@gmail.com>
Requires-Dist: gensim
Requires-Dist: nltk
Requires-Dist: numpy
Requires-Dist: scipy
Requires-Dist: matplotlib
Requires-Dist: keras
Requires-Dist: scikit-learn
Requires-Dist: tensorflow
Requires-Dist: pandas
